cli.py
packers/__init__.py
packers/elf_packer.py
packers/mzip_packer.py
packers/raw_packer.py
packers/rv_packer.py
packers/utils.py
ios_fw-0.1.6.dist-info/entry_points.txt
ios_fw-0.1.6.dist-info/WHEEL
ios_fw-0.1.6.dist-info/METADATA
ios_fw-0.1.6.dist-info/RECORD
