Metadata-Version: 2.1
Name: ios-fw
Version: 0.1.6
Summary: IOS firmware utilities
Author: Charlie Brown
Author-email: whysoyum@gmail.com
Requires-Python: >=3.6,<4.0
Classifier: Programming Language :: Python :: 3
Classifier: Programming Language :: Python :: 3.6
Classifier: Programming Language :: Python :: 3.7
Classifier: Programming Language :: Python :: 3.8
Requires-Dist: click (>=7.1.1,<8.0.0)
Requires-Dist: coloredlogs (>=14.0,<15.0)
Requires-Dist: construct (>=2.10.56,<3.0.0)
Requires-Dist: simpleelf (>=0.1.3,<0.2.0)
